tests/__init__.py
tests/test_datasets.py
tests/test_models.py
tests/test_utils.py
tfrec/__init__.py
tfrec/datasets/__init__.py
tfrec/datasets/ml100k.py
tfrec/models/__init__.py
tfrec/models/svd.py
tfrec/models/svdpp.py
tfrec/utils/__init__.py
tfrec/utils/model_utils.py
tfrec-1.0.0.dist-info/LICENSE
tfrec-1.0.0.dist-info/METADATA
tfrec-1.0.0.dist-info/WHEEL
tfrec-1.0.0.dist-info/top_level.txt
tfrec-1.0.0.dist-info/RECORD
