Metadata-Version: 2.1
Name: tfrec
Version: 1.0.0
Summary: A recommender library built on top of Tensorflow and     Keras with implementations of SVD and SVD++ algorithms.
Home-page: https://github.com/Praful932/tf-rec
Author: Praful Mohanan
Author-email: praful.mohanan@gmail.com
License: MIT
Platform: UNKNOWN
Classifier: Development Status :: 3 - Alpha
Classifier: Programming Language :: Python
Classifier: Programming Language :: Python :: 3.6
Classifier: Programming Language :: Python :: 3.7
Classifier: Programming Language :: Python :: 3.8
Classifier: Operating System :: OS Independent
Classifier: Topic :: Scientific/Engineering
Classifier: License :: OSI Approved :: MIT License
Requires-Python: >=3.6
Requires-Dist: tensorflow (>=2.0)
Requires-Dist: numpy (>=1.18.5)
Requires-Dist: pandas (>=1.1.5)
Requires-Dist: scikit-learn (>=0.22.2)
Requires-Dist: requests
